{
  "table": {
    "schema": "glogowner",
    "name": "partner_item_refnum",
    "description": "This table Contains the reference number for partner item"
  },
  "columns": [
    {
      "name": "DOMAIN_NAME",
      "description": "",
      "dataType": "VARCHAR2",
      "size": 50,
      "isNull": false,
      "isConstraint": false,
      "constraintValues": "",
      "conditionalConstraint": "",
      "defaultValue": ""
    },
    {
      "name": "INSERT_USER",
      "description": "",
      "dataType": "VARCHAR2",
      "size": 128,
      "isNull": false,
      "isConstraint": false,
      "constraintValues": "",
      "conditionalConstraint": "",
      "defaultValue": ""
    },
    {
      "name": "INSERT_DATE",
      "description": "",
      "dataType": "DATE",
      "isNull": false,
      "isConstraint": false,
      "constraintValues": "",
      "conditionalConstraint": "",
      "defaultValue": ""
    },
    {
      "name": "UPDATE_USER",
      "description": "",
      "dataType": "VARCHAR2",
      "size": 128,
      "isNull": true,
      "isConstraint": false,
      "constraintValues": "",
      "conditionalConstraint": "",
      "defaultValue": ""
    },
    {
      "name": "UPDATE_DATE",
      "description": "",
      "dataType": "DATE",
      "isNull": true,
      "isConstraint": false,
      "constraintValues": "",
      "conditionalConstraint": "",
      "defaultValue": ""
    },
    {
      "name": "PARTNER_ITEM_GID",
      "description": "Specifies the unique identifier across all domains for the partner item",
      "dataType": "VARCHAR2",
      "size": 101,
      "isNull": false,
      "isConstraint": false,
      "constraintValues": "",
      "conditionalConstraint": "",
      "defaultValue": ""
    },
    {
      "name": "PARTNER_ITEM_REFNUM_QUAL_GID",
      "description": "The unique trade item reference qualifier id.",
      "dataType": "VARCHAR2",
      "size": 101,
      "isNull": false,
      "isConstraint": false,
      "constraintValues": "",
      "conditionalConstraint": "",
      "defaultValue": ""
    },
    {
      "name": "REFNUM_VALUE",
      "description": "The reference number value for trade item",
      "dataType": "VARCHAR2",
      "size": 240,
      "isNull": false,
      "isConstraint": false,
      "constraintValues": "",
      "conditionalConstraint": "",
      "defaultValue": ""
    }
  ],
  "primaryKey": [
    {
      "sequence": 1,
      "columnName": "PARTNER_ITEM_GID"
    },
    {
      "sequence": 2,
      "columnName": "PARTNER_ITEM_REFNUM_QUAL_GID"
    },
    {
      "sequence": 3,
      "columnName": "REFNUM_VALUE"
    }
  ],
  "foreignKeys": [
    {
      "foreignKeyName": "FK_PIREF_PARTNER_ITEM_GID",
      "cascadeDelete": true,
      "parentTableName": "PARTNER_ITEM",
      "columnRelation": [
        {
          "sequence": 1,
          "parentColumnName": "PARTNER_ITEM_GID",
          "columnName": "PARTNER_ITEM_GID"
        }
      ]
    },
    {
      "foreignKeyName": "FK_PIREF_PARTNER_ITEM_REFNUM",
      "cascadeDelete": false,
      "parentTableName": "PARTNER_ITEM_REFNUM_QUAL",
      "columnRelation": [
        {
          "sequence": 1,
          "parentColumnName": "PARTNER_ITEM_REFNUM_QUAL_GID",
          "columnName": "PARTNER_ITEM_REFNUM_QUAL_GID"
        }
      ]
    }
  ],
  "childTables": [],
  "indices": []
}
