{
  "table": {
    "schema": "glogowner",
    "name": "x_ups_zone",
    "description": "This is a staging table to store the flat file data coming from UPS."
  },
  "columns": [
    {
      "name": "ORIG_ZIP3_LOW",
      "description": "",
      "dataType": "VARCHAR2",
      "size": 15,
      "isNull": false,
      "isConstraint": false,
      "constraintValues": "",
      "conditionalConstraint": "",
      "defaultValue": ""
    },
    {
      "name": "ORIG_ZIP3_HIGH",
      "description": "",
      "dataType": "VARCHAR2",
      "size": 15,
      "isNull": false,
      "isConstraint": false,
      "constraintValues": "",
      "conditionalConstraint": "",
      "defaultValue": ""
    },
    {
      "name": "DEST_ZIP3_LOW",
      "description": "",
      "dataType": "VARCHAR2",
      "size": 15,
      "isNull": false,
      "isConstraint": false,
      "constraintValues": "",
      "conditionalConstraint": "",
      "defaultValue": ""
    },
    {
      "name": "DEST_ZIP3_HIGH",
      "description": "",
      "dataType": "VARCHAR2",
      "size": 15,
      "isNull": false,
      "isConstraint": false,
      "constraintValues": "",
      "conditionalConstraint": "",
      "defaultValue": ""
    },
    {
      "name": "GROUND_ZONE",
      "description": "",
      "dataType": "VARCHAR2",
      "size": 10,
      "isNull": true,
      "isConstraint": false,
      "constraintValues": "",
      "conditionalConstraint": "",
      "defaultValue": ""
    },
    {
      "name": "THREE_DAY_SELECT_ZONE",
      "description": "",
      "dataType": "VARCHAR2",
      "size": 10,
      "isNull": true,
      "isConstraint": false,
      "constraintValues": "",
      "conditionalConstraint": "",
      "defaultValue": ""
    },
    {
      "name": "SEC_DAY_AIR1_ZONE",
      "description": "",
      "dataType": "VARCHAR2",
      "size": 10,
      "isNull": true,
      "isConstraint": false,
      "constraintValues": "",
      "conditionalConstraint": "",
      "defaultValue": ""
    },
    {
      "name": "SEC_DAY_AIR2_ZONE",
      "description": "",
      "dataType": "VARCHAR2",
      "size": 10,
      "isNull": true,
      "isConstraint": false,
      "constraintValues": "",
      "conditionalConstraint": "",
      "defaultValue": ""
    },
    {
      "name": "NEXT_DAY_AIR1_ZONE",
      "description": "",
      "dataType": "VARCHAR2",
      "size": 10,
      "isNull": true,
      "isConstraint": false,
      "constraintValues": "",
      "conditionalConstraint": "",
      "defaultValue": ""
    },
    {
      "name": "NEXT_DAY_AIR2_ZONE",
      "description": "",
      "dataType": "VARCHAR2",
      "size": 10,
      "isNull": true,
      "isConstraint": false,
      "constraintValues": "",
      "conditionalConstraint": "",
      "defaultValue": ""
    }
  ],
  "primaryKey": [],
  "foreignKeys": [],
  "childTables": [],
  "indices": []
}
