{
  "cacheType": "OTM_OBJECT_CACHE",
  "version": "1.0",
  "generatedAt": "2026-02-24T18:58:01Z",
  "source": "update_otm_object_cache.py",
  "migrationItem": {
    "migrationItemId": "MIGRATION_ITEM.PLANNING.LOAD_CONFIG_SETUP_ORIENTATION.LOAD_CONFIG_SETUP_ORIENTATION_AUTO.144",
    "migrationItemName": "LOAD_CONFIG_SETUP_ORIENTATION (AUTO)",
    "migrationGroupId": "PLANNING",
    "objectType": "LOAD_CONFIG_SETUP_ORIENTATION",
    "otmTable": "LOAD_CONFIG_SETUP_ORIENTATION",
    "otmSubtables": [],
    "domainName": "BAU",
    "sequence": 144,
    "deploymentType": "MIGRATION_PROJECT"
  },
  "object": {
    "name": "LOAD_CONFIG_SETUP_ORIENTATION (AUTO)",
    "groupId": "PLANNING",
    "objectType": "LOAD_CONFIG_SETUP_ORIENTATION",
    "otmTable": "LOAD_CONFIG_SETUP_ORIENTATION",
    "domainName": "BAU",
    "sequence": 144,
    "deploymentType": "MIGRATION_PROJECT"
  },
  "extraction": {
    "objectExtractionQueryLanguage": "SQL",
    "objectExtractionQuerySource": "object_extraction_query",
    "technicalContentType": "NONE",
    "rootName": "LOAD_CONFIG_SETUP_ORIENTATION",
    "query": "SELECT *\nFROM\n  LOAD_CONFIG_SETUP LCS\n  JOIN LOAD_CONFIG_SETUP_ORIENTATION LCSO\n    ON LCSO.LOAD_CONFIG_SETUP_GID = LCS.LOAD_CONFIG_SETUP_GID\n    AND LCSO.DOMAIN_NAME = LCS.DOMAIN_NAME\nWHERE\n  LCS.DOMAIN_NAME = 'BAU'\nORDER BY\n  LCS.LOAD_CONFIG_SETUP_GID,\n  LCSO.ORIENTATION_GID",
    "normalizedRowCount": 6,
    "nonSchemaFieldsDetected": [
      "IS_FOR_SHIP_UNIT_BUILDING",
      "IS_STACKABLE_ABOVE",
      "IS_STACKABLE_BELOW",
      "LOAD_CONFIG_SETUP_XID"
    ],
    "tableCount": 1,
    "tableNames": [
      "LOAD_CONFIG_SETUP_ORIENTATION"
    ],
    "skippedSubtablesNoSchema": []
  },
  "tableHierarchy": {
    "primaryTable": "LOAD_CONFIG_SETUP_ORIENTATION",
    "subtables": [],
    "allTables": [
      "LOAD_CONFIG_SETUP_ORIENTATION"
    ],
    "skippedSubtablesNoSchema": []
  },
  "tables": {
    "LOAD_CONFIG_SETUP_ORIENTATION": {
      "tableName": "LOAD_CONFIG_SETUP_ORIENTATION",
      "schema": {
        "owner": "glogowner",
        "tableName": "load_config_setup_orientation",
        "columnCount": 18,
        "columns": [
          "DOMAIN_NAME",
          "INSERT_USER",
          "INSERT_DATE",
          "UPDATE_USER",
          "UPDATE_DATE",
          "LOAD_CONFIG_SETUP_GID",
          "ORIENTATION_GID",
          "IS_PREFERRED",
          "IS_FLOOR_COMPATIBLE",
          "MAX_TOP_WEIGHT",
          "MAX_TOP_WEIGHT_UOM_CODE",
          "MAX_TOP_WEIGHT_BASE",
          "MAX_LENGTH_OVERHANG",
          "MAX_LENGTH_OVERHANG_UOM_CODE",
          "MAX_LENGTH_OVERHANG_BASE",
          "MAX_WIDTH_OVERHANG",
          "MAX_WIDTH_OVERHANG_UOM_CODE",
          "MAX_WIDTH_OVERHANG_BASE"
        ]
      },
      "extraction": {
        "queryLanguage": "SQL",
        "querySource": "object_extraction_query",
        "rootName": "LOAD_CONFIG_SETUP_ORIENTATION",
        "query": "SELECT *\nFROM\n  LOAD_CONFIG_SETUP LCS\n  JOIN LOAD_CONFIG_SETUP_ORIENTATION LCSO\n    ON LCSO.LOAD_CONFIG_SETUP_GID = LCS.LOAD_CONFIG_SETUP_GID\n    AND LCSO.DOMAIN_NAME = LCS.DOMAIN_NAME\nWHERE\n  LCS.DOMAIN_NAME = 'BAU'\nORDER BY\n  LCS.LOAD_CONFIG_SETUP_GID,\n  LCSO.ORIENTATION_GID",
        "normalizedRowCount": 6,
        "nonSchemaFieldsDetected": [
          "IS_FOR_SHIP_UNIT_BUILDING",
          "IS_STACKABLE_ABOVE",
          "IS_STACKABLE_BELOW",
          "LOAD_CONFIG_SETUP_XID"
        ]
      },
      "rows": [
        {
          "DOMAIN_NAME": "BAU",
          "INSERT_USER": "",
          "INSERT_DATE": "2026-02-11T23:02:52Z",
          "UPDATE_USER": "",
          "UPDATE_DATE": "",
          "LOAD_CONFIG_SETUP_GID": "BAU.PALLET_MIX",
          "ORIENTATION_GID": "UPRIGHT LENGTHWISE",
          "IS_PREFERRED": "N",
          "IS_FLOOR_COMPATIBLE": "Y",
          "MAX_TOP_WEIGHT": "",
          "MAX_TOP_WEIGHT_UOM_CODE": "",
          "MAX_TOP_WEIGHT_BASE": "",
          "MAX_LENGTH_OVERHANG": "",
          "MAX_LENGTH_OVERHANG_UOM_CODE": "",
          "MAX_LENGTH_OVERHANG_BASE": "",
          "MAX_WIDTH_OVERHANG": "",
          "MAX_WIDTH_OVERHANG_UOM_CODE": "",
          "MAX_WIDTH_OVERHANG_BASE": ""
        },
        {
          "DOMAIN_NAME": "BAU",
          "INSERT_USER": "",
          "INSERT_DATE": "2026-02-11T23:02:52Z",
          "UPDATE_USER": "",
          "UPDATE_DATE": "",
          "LOAD_CONFIG_SETUP_GID": "BAU.PALLET_MIX",
          "ORIENTATION_GID": "UPRIGHT WIDTHWISE",
          "IS_PREFERRED": "Y",
          "IS_FLOOR_COMPATIBLE": "Y",
          "MAX_TOP_WEIGHT": "",
          "MAX_TOP_WEIGHT_UOM_CODE": "",
          "MAX_TOP_WEIGHT_BASE": "",
          "MAX_LENGTH_OVERHANG": "",
          "MAX_LENGTH_OVERHANG_UOM_CODE": "",
          "MAX_LENGTH_OVERHANG_BASE": "",
          "MAX_WIDTH_OVERHANG": "",
          "MAX_WIDTH_OVERHANG_UOM_CODE": "",
          "MAX_WIDTH_OVERHANG_BASE": ""
        },
        {
          "DOMAIN_NAME": "BAU",
          "INSERT_USER": "",
          "INSERT_DATE": "2026-02-11T23:02:52Z",
          "UPDATE_USER": "",
          "UPDATE_DATE": "",
          "LOAD_CONFIG_SETUP_GID": "BAU.PALLET_PBA",
          "ORIENTATION_GID": "UPRIGHT LENGTHWISE",
          "IS_PREFERRED": "N",
          "IS_FLOOR_COMPATIBLE": "Y",
          "MAX_TOP_WEIGHT": "",
          "MAX_TOP_WEIGHT_UOM_CODE": "",
          "MAX_TOP_WEIGHT_BASE": "",
          "MAX_LENGTH_OVERHANG": "",
          "MAX_LENGTH_OVERHANG_UOM_CODE": "",
          "MAX_LENGTH_OVERHANG_BASE": "",
          "MAX_WIDTH_OVERHANG": "",
          "MAX_WIDTH_OVERHANG_UOM_CODE": "",
          "MAX_WIDTH_OVERHANG_BASE": ""
        },
        {
          "DOMAIN_NAME": "BAU",
          "INSERT_USER": "",
          "INSERT_DATE": "2026-02-11T23:02:52Z",
          "UPDATE_USER": "",
          "UPDATE_DATE": "",
          "LOAD_CONFIG_SETUP_GID": "BAU.PALLET_PBA",
          "ORIENTATION_GID": "UPRIGHT WIDTHWISE",
          "IS_PREFERRED": "Y",
          "IS_FLOOR_COMPATIBLE": "Y",
          "MAX_TOP_WEIGHT": "",
          "MAX_TOP_WEIGHT_UOM_CODE": "",
          "MAX_TOP_WEIGHT_BASE": "",
          "MAX_LENGTH_OVERHANG": "",
          "MAX_LENGTH_OVERHANG_UOM_CODE": "",
          "MAX_LENGTH_OVERHANG_BASE": "",
          "MAX_WIDTH_OVERHANG": "",
          "MAX_WIDTH_OVERHANG_UOM_CODE": "",
          "MAX_WIDTH_OVERHANG_BASE": ""
        },
        {
          "DOMAIN_NAME": "BAU",
          "INSERT_USER": "",
          "INSERT_DATE": "2026-02-11T23:02:52Z",
          "UPDATE_USER": "",
          "UPDATE_DATE": "",
          "LOAD_CONFIG_SETUP_GID": "BAU.PALLET_PBA_STK",
          "ORIENTATION_GID": "UPRIGHT LENGTHWISE",
          "IS_PREFERRED": "N",
          "IS_FLOOR_COMPATIBLE": "Y",
          "MAX_TOP_WEIGHT": "",
          "MAX_TOP_WEIGHT_UOM_CODE": "",
          "MAX_TOP_WEIGHT_BASE": "",
          "MAX_LENGTH_OVERHANG": "",
          "MAX_LENGTH_OVERHANG_UOM_CODE": "",
          "MAX_LENGTH_OVERHANG_BASE": "",
          "MAX_WIDTH_OVERHANG": "",
          "MAX_WIDTH_OVERHANG_UOM_CODE": "",
          "MAX_WIDTH_OVERHANG_BASE": ""
        },
        {
          "DOMAIN_NAME": "BAU",
          "INSERT_USER": "",
          "INSERT_DATE": "2026-02-11T23:02:52Z",
          "UPDATE_USER": "",
          "UPDATE_DATE": "",
          "LOAD_CONFIG_SETUP_GID": "BAU.PALLET_PBA_STK",
          "ORIENTATION_GID": "UPRIGHT WIDTHWISE",
          "IS_PREFERRED": "Y",
          "IS_FLOOR_COMPATIBLE": "Y",
          "MAX_TOP_WEIGHT": "",
          "MAX_TOP_WEIGHT_UOM_CODE": "",
          "MAX_TOP_WEIGHT_BASE": "",
          "MAX_LENGTH_OVERHANG": "",
          "MAX_LENGTH_OVERHANG_UOM_CODE": "",
          "MAX_LENGTH_OVERHANG_BASE": "",
          "MAX_WIDTH_OVERHANG": "",
          "MAX_WIDTH_OVERHANG_UOM_CODE": "",
          "MAX_WIDTH_OVERHANG_BASE": ""
        }
      ]
    }
  },
  "schema": {
    "owner": "glogowner",
    "tableName": "load_config_setup_orientation",
    "columnCount": 18,
    "columns": [
      "DOMAIN_NAME",
      "INSERT_USER",
      "INSERT_DATE",
      "UPDATE_USER",
      "UPDATE_DATE",
      "LOAD_CONFIG_SETUP_GID",
      "ORIENTATION_GID",
      "IS_PREFERRED",
      "IS_FLOOR_COMPATIBLE",
      "MAX_TOP_WEIGHT",
      "MAX_TOP_WEIGHT_UOM_CODE",
      "MAX_TOP_WEIGHT_BASE",
      "MAX_LENGTH_OVERHANG",
      "MAX_LENGTH_OVERHANG_UOM_CODE",
      "MAX_LENGTH_OVERHANG_BASE",
      "MAX_WIDTH_OVERHANG",
      "MAX_WIDTH_OVERHANG_UOM_CODE",
      "MAX_WIDTH_OVERHANG_BASE"
    ]
  },
  "rows": [
    {
      "DOMAIN_NAME": "BAU",
      "INSERT_USER": "",
      "INSERT_DATE": "2026-02-11T23:02:52Z",
      "UPDATE_USER": "",
      "UPDATE_DATE": "",
      "LOAD_CONFIG_SETUP_GID": "BAU.PALLET_MIX",
      "ORIENTATION_GID": "UPRIGHT LENGTHWISE",
      "IS_PREFERRED": "N",
      "IS_FLOOR_COMPATIBLE": "Y",
      "MAX_TOP_WEIGHT": "",
      "MAX_TOP_WEIGHT_UOM_CODE": "",
      "MAX_TOP_WEIGHT_BASE": "",
      "MAX_LENGTH_OVERHANG": "",
      "MAX_LENGTH_OVERHANG_UOM_CODE": "",
      "MAX_LENGTH_OVERHANG_BASE": "",
      "MAX_WIDTH_OVERHANG": "",
      "MAX_WIDTH_OVERHANG_UOM_CODE": "",
      "MAX_WIDTH_OVERHANG_BASE": ""
    },
    {
      "DOMAIN_NAME": "BAU",
      "INSERT_USER": "",
      "INSERT_DATE": "2026-02-11T23:02:52Z",
      "UPDATE_USER": "",
      "UPDATE_DATE": "",
      "LOAD_CONFIG_SETUP_GID": "BAU.PALLET_MIX",
      "ORIENTATION_GID": "UPRIGHT WIDTHWISE",
      "IS_PREFERRED": "Y",
      "IS_FLOOR_COMPATIBLE": "Y",
      "MAX_TOP_WEIGHT": "",
      "MAX_TOP_WEIGHT_UOM_CODE": "",
      "MAX_TOP_WEIGHT_BASE": "",
      "MAX_LENGTH_OVERHANG": "",
      "MAX_LENGTH_OVERHANG_UOM_CODE": "",
      "MAX_LENGTH_OVERHANG_BASE": "",
      "MAX_WIDTH_OVERHANG": "",
      "MAX_WIDTH_OVERHANG_UOM_CODE": "",
      "MAX_WIDTH_OVERHANG_BASE": ""
    },
    {
      "DOMAIN_NAME": "BAU",
      "INSERT_USER": "",
      "INSERT_DATE": "2026-02-11T23:02:52Z",
      "UPDATE_USER": "",
      "UPDATE_DATE": "",
      "LOAD_CONFIG_SETUP_GID": "BAU.PALLET_PBA",
      "ORIENTATION_GID": "UPRIGHT LENGTHWISE",
      "IS_PREFERRED": "N",
      "IS_FLOOR_COMPATIBLE": "Y",
      "MAX_TOP_WEIGHT": "",
      "MAX_TOP_WEIGHT_UOM_CODE": "",
      "MAX_TOP_WEIGHT_BASE": "",
      "MAX_LENGTH_OVERHANG": "",
      "MAX_LENGTH_OVERHANG_UOM_CODE": "",
      "MAX_LENGTH_OVERHANG_BASE": "",
      "MAX_WIDTH_OVERHANG": "",
      "MAX_WIDTH_OVERHANG_UOM_CODE": "",
      "MAX_WIDTH_OVERHANG_BASE": ""
    },
    {
      "DOMAIN_NAME": "BAU",
      "INSERT_USER": "",
      "INSERT_DATE": "2026-02-11T23:02:52Z",
      "UPDATE_USER": "",
      "UPDATE_DATE": "",
      "LOAD_CONFIG_SETUP_GID": "BAU.PALLET_PBA",
      "ORIENTATION_GID": "UPRIGHT WIDTHWISE",
      "IS_PREFERRED": "Y",
      "IS_FLOOR_COMPATIBLE": "Y",
      "MAX_TOP_WEIGHT": "",
      "MAX_TOP_WEIGHT_UOM_CODE": "",
      "MAX_TOP_WEIGHT_BASE": "",
      "MAX_LENGTH_OVERHANG": "",
      "MAX_LENGTH_OVERHANG_UOM_CODE": "",
      "MAX_LENGTH_OVERHANG_BASE": "",
      "MAX_WIDTH_OVERHANG": "",
      "MAX_WIDTH_OVERHANG_UOM_CODE": "",
      "MAX_WIDTH_OVERHANG_BASE": ""
    },
    {
      "DOMAIN_NAME": "BAU",
      "INSERT_USER": "",
      "INSERT_DATE": "2026-02-11T23:02:52Z",
      "UPDATE_USER": "",
      "UPDATE_DATE": "",
      "LOAD_CONFIG_SETUP_GID": "BAU.PALLET_PBA_STK",
      "ORIENTATION_GID": "UPRIGHT LENGTHWISE",
      "IS_PREFERRED": "N",
      "IS_FLOOR_COMPATIBLE": "Y",
      "MAX_TOP_WEIGHT": "",
      "MAX_TOP_WEIGHT_UOM_CODE": "",
      "MAX_TOP_WEIGHT_BASE": "",
      "MAX_LENGTH_OVERHANG": "",
      "MAX_LENGTH_OVERHANG_UOM_CODE": "",
      "MAX_LENGTH_OVERHANG_BASE": "",
      "MAX_WIDTH_OVERHANG": "",
      "MAX_WIDTH_OVERHANG_UOM_CODE": "",
      "MAX_WIDTH_OVERHANG_BASE": ""
    },
    {
      "DOMAIN_NAME": "BAU",
      "INSERT_USER": "",
      "INSERT_DATE": "2026-02-11T23:02:52Z",
      "UPDATE_USER": "",
      "UPDATE_DATE": "",
      "LOAD_CONFIG_SETUP_GID": "BAU.PALLET_PBA_STK",
      "ORIENTATION_GID": "UPRIGHT WIDTHWISE",
      "IS_PREFERRED": "Y",
      "IS_FLOOR_COMPATIBLE": "Y",
      "MAX_TOP_WEIGHT": "",
      "MAX_TOP_WEIGHT_UOM_CODE": "",
      "MAX_TOP_WEIGHT_BASE": "",
      "MAX_LENGTH_OVERHANG": "",
      "MAX_LENGTH_OVERHANG_UOM_CODE": "",
      "MAX_LENGTH_OVERHANG_BASE": "",
      "MAX_WIDTH_OVERHANG": "",
      "MAX_WIDTH_OVERHANG_UOM_CODE": "",
      "MAX_WIDTH_OVERHANG_BASE": ""
    }
  ]
}
